LICENSE
MANIFEST.in
README.rst
setup.py
hulu/__init__.py
hulu/api.py
hulu/compat.py
hulu/exceptions.py
hulu.egg-info/PKG-INFO
hulu.egg-info/SOURCES.txt
hulu.egg-info/dependency_links.txt
hulu.egg-info/requires.txt
hulu.egg-info/top_level.txt