Metadata-Version: 1.0
Name: hulu
Version: 0.1.0
Summary: A Python library to interact with Hulu's "hidden" 2.0 API.
Home-page: http://github.com/michaelhelmick/hulu/tree/master
Author: Mike Helmick
Author-email: mikehelmick@me.com
License: Copyright (c) 2013, Mike Helmick
